XYXY-0.2.4.dist-info/DESCRIPTION.rst
XYXY-0.2.4.dist-info/METADATA
XYXY-0.2.4.dist-info/RECORD
XYXY-0.2.4.dist-info/WHEEL
XYXY-0.2.4.dist-info/metadata.json
XYXY-0.2.4.dist-info/top_level.txt
tests/__init__.py
tests/test_test.py
xyxy/__init__.py
xyxy/config.py
xyxy/formula.py
xyxy/helper.py
xyxy/loader.py
